README.rst
setup.py
anybox/__init__.py
anybox.buildbot.capability.egg-info/PKG-INFO
anybox.buildbot.capability.egg-info/SOURCES.txt
anybox.buildbot.capability.egg-info/dependency_links.txt
anybox.buildbot.capability.egg-info/entry_points.txt
anybox.buildbot.capability.egg-info/namespace_packages.txt
anybox.buildbot.capability.egg-info/not-zip-safe
anybox.buildbot.capability.egg-info/requires.txt
anybox.buildbot.capability.egg-info/top_level.txt
anybox/buildbot/__init__.py
anybox/buildbot/capability/__init__.py
anybox/buildbot/capability/constants.py
anybox/buildbot/capability/dispatcher.py
anybox/buildbot/capability/steps.py
anybox/buildbot/capability/version.py
anybox/buildbot/capability/tests/__init__.py
anybox/buildbot/capability/tests/test_dispatcher.py
anybox/buildbot/capability/tests/test_steps.py