Metadata-Version: 1.1
Name: anybox.buildbot.capability
Version: 0.1
Summary: Static capability system for buildbot
Home-page: http://pypi.python.org/pypi/anybox.buildbot.odoo
Author: Anybox SAS
Author-email: gracinet@anybox.fr
License: GPLv2+
Platform: UNKNOWN
Classifier: Intended Audience :: Developers
Classifier: Intended Audience :: System Administrators
Classifier: Topic :: Software Development :: Build Tools
Classifier: Topic :: Software Development :: Testing
Classifier: Topic :: Software Development :: Quality Assurance
Classifier: Topic :: Software Development :: Libraries :: Python Modules
Classifier: License :: OSI Approved :: GNU General Public License v2 or later (GPLv2+)
